castle/__init__.py
castle/api_request.py
castle/client.py
castle/command.py
castle/configuration.py
castle/errors.py
castle/logger.py
castle/secure_mode.py
castle/session.py
castle/verdict.py
castle/version.py
castle/api/__init__.py
castle/api/approve_device.py
castle/api/get_device.py
castle/api/get_devices_for_user.py
castle/api/report_device.py
castle/client_id/__init__.py
castle/client_id/extract.py
castle/commands/__init__.py
castle/commands/approve_device.py
castle/commands/authenticate.py
castle/commands/end_impersonation.py
castle/commands/filter.py
castle/commands/get_device.py
castle/commands/get_devices_for_user.py
castle/commands/log.py
castle/commands/report_device.py
castle/commands/risk.py
castle/commands/start_impersonation.py
castle/commands/track.py
castle/context/__init__.py
castle/context/get_default.py
castle/context/merge.py
castle/context/prepare.py
castle/context/sanitize.py
castle/core/__init__.py
castle/core/process_response.py
castle/core/process_webhook.py
castle/core/send_request.py
castle/failover/__init__.py
castle/failover/prepare_response.py
castle/failover/strategy.py
castle/headers/__init__.py
castle/headers/extract.py
castle/headers/filter.py
castle/headers/format.py
castle/ips/__init__.py
castle/ips/extract.py
castle/payload/__init__.py
castle/payload/prepare.py
castle/test/__init__.py
castle/test/api_request_test.py
castle/test/client_test.py
castle/test/command_test.py
castle/test/configuration_test.py
castle/test/logger_test.py
castle/test/secure_mode_test.py
castle/test/session_test.py
castle/test/verdict_test.py
castle/utils/__init__.py
castle/utils/clone.py
castle/utils/merge.py
castle/utils/secure_compare.py
castle/utils/timestamp.py
castle/validators/__init__.py
castle/validators/not_supported.py
castle/validators/present.py
castle/webhooks/__init__.py
castle/webhooks/verify.py
castle-6.1.0.dist-info/LICENSE
castle-6.1.0.dist-info/METADATA
castle-6.1.0.dist-info/WHEEL
castle-6.1.0.dist-info/top_level.txt
castle-6.1.0.dist-info/RECORD
